xbos_services_getter/__init__.py
xbos_services_getter/xbos_services_getter.py
xbos_services_getter/lib/__init__.py
xbos_services_getter/lib/baseline_optimizer_pb2.py
xbos_services_getter/lib/baseline_optimizer_pb2_grpc.py
xbos_services_getter/lib/building_zone_names_pb2.py
xbos_services_getter/lib/building_zone_names_pb2_grpc.py
xbos_services_getter/lib/discomfort_pb2.py
xbos_services_getter/lib/discomfort_pb2_grpc.py
xbos_services_getter/lib/hvac_consumption_pb2.py
xbos_services_getter/lib/hvac_consumption_pb2_grpc.py
xbos_services_getter/lib/indoor_data_historical_pb2.py
xbos_services_getter/lib/indoor_data_historical_pb2_grpc.py
xbos_services_getter/lib/indoor_temperature_prediction_pb2.py
xbos_services_getter/lib/indoor_temperature_prediction_pb2_grpc.py
xbos_services_getter/lib/meter_data_historical_pb2.py
xbos_services_getter/lib/meter_data_historical_pb2_grpc.py
xbos_services_getter/lib/occupancy_pb2.py
xbos_services_getter/lib/occupancy_pb2_grpc.py
xbos_services_getter/lib/optimizer_pb2.py
xbos_services_getter/lib/optimizer_pb2_grpc.py
xbos_services_getter/lib/outdoor_temperature_historical_pb2.py
xbos_services_getter/lib/outdoor_temperature_historical_pb2_grpc.py
xbos_services_getter/lib/outdoor_temperature_prediction_pb2.py
xbos_services_getter/lib/outdoor_temperature_prediction_pb2_grpc.py
xbos_services_getter/lib/price_pb2.py
xbos_services_getter/lib/price_pb2_grpc.py
xbos_services_getter/lib/skyspark_pb2.py
xbos_services_getter/lib/skyspark_pb2_grpc.py
xbos_services_getter/lib/temperature_bands_pb2.py
xbos_services_getter/lib/temperature_bands_pb2_grpc.py
xbos_services_getter/test/__init__.py
xbos_services_getter/test/test.py
xbos_services_getter-0.0.2.dev47.dist-info/METADATA
xbos_services_getter-0.0.2.dev47.dist-info/WHEEL
xbos_services_getter-0.0.2.dev47.dist-info/top_level.txt
xbos_services_getter-0.0.2.dev47.dist-info/RECORD
