Metadata-Version: 2.1
Name: xbos-services-getter
Version: 0.0.2.dev47
Summary: Getter functions for xbos services using Python 3.6.
Home-page: UNKNOWN
Author: Daniel Lengyel
Author-email: daniel.lengyel@berkeley.edu
License: UNKNOWN
Platform: UNKNOWN
Requires-Dist: pandas (==0.24.0)
Requires-Dist: pytz (>=2017.2)
Requires-Dist: grpcio (==1.16.1)
Requires-Dist: grpcio-tools (==1.16.1)
